{"country": "HN", "date_of_birth": "2015/03/24", "mother_name": "ZALDIVAR TORRES", "countries_likely_to_be_visited": ["US"], "mother_forename": "KAREN LIZETH", "nationalities": null, "eyes_colors_id": null, "sex_id": "F", "forename": "THANIA FERNANDA", "country_of_birth_id": "HN", "issuing_country": "HN", "hairs_id": null, "place": "Aldea los patos, Tela Atl\u00e1ntida", "languages_spoken_ids": null, "date_of_event": "2022/01/23", "height": null, "father_forename": "MELVIN JOSE", "distinguishing_marks": null, "birth_name": null, "weight": null, "entity_id": "2022/8957", "place_of_birth": "La Ceiba,Atlantida", "father_name": "FIGUEROA RAMIREZ", "name": "FIGUEROA ZALDIVAR", "_embedded": {"links": []}, "_links": {"self": {"href": "https://ws-public.interpol.int/notices/v1/yellow/2022-8957"}, "images": {"href": "https://ws-public.interpol.int/notices/v1/yellow/2022-8957/images"}, "thumbnail": {"href": "https://ws-public.interpol.int/notices/v1/yellow/2022-8957/images/62363065"}}}