{"country": "CO", "date_of_birth": "2011/12/09", "mother_name": "RAMOS VALBUENA", "countries_likely_to_be_visited": ["VE"], "mother_forename": "Jelis Chiquinquira", "nationalities": ["VE"], "eyes_colors_id": null, "sex_id": "F", "forename": "JEILIANA ALEJANDRA", "country_of_birth_id": "VE", "issuing_country": "CO", "hairs_id": null, "place": "BOGOT\u00c1 D.C-CUNDINAMARCA", "languages_spoken_ids": ["SPA"], "date_of_event": "2020/01/14", "height": null, "father_forename": "Jos\u00e9 Jesus", "distinguishing_marks": null, "birth_name": "BOSC\u00c1N RAMOS", "weight": null, "entity_id": "2020/4856", "place_of_birth": "Zulia", "father_name": "BOSC\u00c1N CHAPARRO", "name": "BOSC\u00c1N RAMOS", "_embedded": {"links": []}, "_links": {"self": {"href": "https://ws-public.interpol.int/notices/v1/yellow/2020-4856"}, "images": {"href": "https://ws-public.interpol.int/notices/v1/yellow/2020-4856/images"}, "thumbnail": {"href": "https://ws-public.interpol.int/notices/v1/yellow/2020-4856/images/61696210"}}}