{"country": "HN", "date_of_birth": "2017/06/01", "mother_name": "AGUILERA OSEGUERA", "countries_likely_to_be_visited": ["US"], "mother_forename": "ALICIA AYDEE", "nationalities": ["HN"], "eyes_colors_id": null, "sex_id": "M", "forename": "ALLAN JOEL", "country_of_birth_id": "HN", "issuing_country": "HN", "hairs_id": null, "place": "Barrio La Maria, Marcovia Choluteca", "languages_spoken_ids": null, "date_of_event": "2022/09/25", "height": null, "father_forename": "KEVIN JOEL", "distinguishing_marks": null, "birth_name": null, "weight": null, "entity_id": "2022/67206", "place_of_birth": "Marcovia, Choluteca", "father_name": "RIVAS DIAZ", "name": "RIVAS AGUILERA", "_embedded": {"links": []}, "_links": {"self": {"href": "https://ws-public.interpol.int/notices/v1/yellow/2022-67206"}, "images": {"href": "https://ws-public.interpol.int/notices/v1/yellow/2022-67206/images"}, "thumbnail": {"href": "https://ws-public.interpol.int/notices/v1/yellow/2022-67206/images/62566071"}}}