{"date_of_birth": "1993/04/15", "distinguishing_marks": null, "weight": null, "nationalities": ["PY"], "entity_id": "2019/95682", "eyes_colors_id": null, "sex_id": "M", "place_of_birth": null, "forename": "ELIAS", "arrest_warrants": [{"charge": "HOMICIDIO AGRAVADO POR CONCURSO PREMEDITADO DE DOS O M\u00c1S PERSONAS", "issuing_country_id": "AR", "charge_translation": null}], "country_of_birth_id": "PY", "hairs_id": null, "name": "ACOSTA ACOSTA", "languages_spoken_ids": ["SPA"], "height": null, "_embedded": {"links": []}, "_links": {"self": {"href": "https://ws-public.interpol.int/notices/v1/red/2019-95682"}, "images": {"href": "https://ws-public.interpol.int/notices/v1/red/2019-95682/images"}, "thumbnail": {"href": "https://ws-public.interpol.int/notices/v1/red/2019-95682/images/61550726"}}}