{"country": "GT", "date_of_birth": "2011/10/22", "mother_name": "QUICHIEJ", "countries_likely_to_be_visited": ["MX", "SV", "PA", "NI", "CR", null, "US", "HN"], "mother_forename": "RUTH", "nationalities": ["GT"], "eyes_colors_id": ["BROD"], "sex_id": "M", "forename": "ANGEL ALBERTO", "country_of_birth_id": "GT", "issuing_country": "GT", "hairs_id": ["BLA"], "place": "MUNICIPIO DE VILLA NUEVA, DEPARTAMENTO DE GUATEMALA", "languages_spoken_ids": ["SPA"], "date_of_event": "2021/04/27", "height": 1.28, "father_forename": "CARLOS", "distinguishing_marks": null, "birth_name": null, "weight": 110, "entity_id": "2021/32163", "place_of_birth": "GUATEMALA", "father_name": "RODAS", "name": "RODAS CHIQUIEJ", "_embedded": {"links": []}, "_links": {"self": {"href": "https://ws-public.interpol.int/notices/v1/yellow/2021-32163"}, "images": {"href": "https://ws-public.interpol.int/notices/v1/yellow/2021-32163/images"}, "thumbnail": {"href": "https://ws-public.interpol.int/notices/v1/yellow/2021-32163/images/62140548"}}}