{"date_of_birth": "1994/09/24", "distinguishing_marks": null, "weight": 60, "nationalities": ["SV"], "entity_id": "2018/43998", "eyes_colors_id": ["OTHD"], "sex_id": "M", "place_of_birth": null, "forename": "KEVIN ALEXANDER", "arrest_warrants": [{"charge": "ORGANIZACIONES TERRORISTAS", "issuing_country_id": "SV", "charge_translation": null}], "country_of_birth_id": null, "hairs_id": ["BLA"], "name": "BARAHONA FUNES", "languages_spoken_ids": ["SPA"], "height": 1.69, "_embedded": {"links": []}, "_links": {"self": {"href": "https://ws-public.interpol.int/notices/v1/red/2018-43998"}, "images": {"href": "https://ws-public.interpol.int/notices/v1/red/2018-43998/images"}, "thumbnail": {"href": "https://ws-public.interpol.int/notices/v1/red/2018-43998/images/61049834"}}}