{"country": "CL", "date_of_birth": "2007/08/15", "mother_name": null, "countries_likely_to_be_visited": ["PE", "MX", "CO", "US"], "mother_forename": null, "nationalities": ["HT"], "eyes_colors_id": null, "sex_id": "M", "forename": "WATSON", "country_of_birth_id": "HT", "issuing_country": "CL", "hairs_id": null, "place": null, "languages_spoken_ids": ["SPA"], "date_of_event": "2023/10/13", "height": null, "father_forename": null, "distinguishing_marks": null, "birth_name": "JEAN PHILIPPE", "weight": null, "entity_id": "2023/67123", "place_of_birth": null, "father_name": null, "name": "JEAN PHILIPPE", "_embedded": {"links": []}, "_links": {"self": {"href": "https://ws-public.interpol.int/notices/v1/yellow/2023-67123"}, "images": {"href": "https://ws-public.interpol.int/notices/v1/yellow/2023-67123/images"}, "thumbnail": {"href": "https://ws-public.interpol.int/notices/v1/yellow/2023-67123/images/62879138"}}}