{"date_of_birth": "1994/06/13", "distinguishing_marks": null, "weight": null, "nationalities": ["SV"], "entity_id": "2023/17209", "eyes_colors_id": null, "sex_id": "M", "place_of_birth": "Ciudad de Izalco departamento de  Sonsonate", "forename": "DOUGLAS EDGARDO", "arrest_warrants": [{"charge": "Agrupaciones Il\u00edcitas", "issuing_country_id": "SV", "charge_translation": null}], "country_of_birth_id": "SV", "hairs_id": null, "name": "CENTENO TEJADA", "languages_spoken_ids": ["SPA"], "height": null, "_embedded": {"links": []}, "_links": {"self": {"href": "https://ws-public.interpol.int/notices/v1/red/2023-17209"}, "images": {"href": "https://ws-public.interpol.int/notices/v1/red/2023-17209/images"}, "thumbnail": {"href": "https://ws-public.interpol.int/notices/v1/red/2023-17209/images/62690725"}}}